sqlalchemy_migrate_hotoffthehamster/__init__.py
sqlalchemy_migrate_hotoffthehamster/changeset/__init__.py
sqlalchemy_migrate_hotoffthehamster/changeset/ansisql.py
sqlalchemy_migrate_hotoffthehamster/changeset/constraint.py
sqlalchemy_migrate_hotoffthehamster/changeset/databases/__init__.py
sqlalchemy_migrate_hotoffthehamster/changeset/databases/firebird.py
sqlalchemy_migrate_hotoffthehamster/changeset/databases/ibmdb2.py
sqlalchemy_migrate_hotoffthehamster/changeset/databases/mysql.py
sqlalchemy_migrate_hotoffthehamster/changeset/databases/oracle.py
sqlalchemy_migrate_hotoffthehamster/changeset/databases/postgres.py
sqlalchemy_migrate_hotoffthehamster/changeset/databases/sqlite.py
sqlalchemy_migrate_hotoffthehamster/changeset/databases/visitor.py
sqlalchemy_migrate_hotoffthehamster/changeset/schema.py
sqlalchemy_migrate_hotoffthehamster/changeset/util.py
sqlalchemy_migrate_hotoffthehamster/exceptions.py
sqlalchemy_migrate_hotoffthehamster/tests/__init__.py
sqlalchemy_migrate_hotoffthehamster/tests/fixture/__init__.py
sqlalchemy_migrate_hotoffthehamster/tests/fixture/base.py
sqlalchemy_migrate_hotoffthehamster/tests/fixture/database.py
sqlalchemy_migrate_hotoffthehamster/tests/fixture/models.py
sqlalchemy_migrate_hotoffthehamster/tests/fixture/pathed.py
sqlalchemy_migrate_hotoffthehamster/tests/fixture/shell.py
sqlalchemy_migrate_hotoffthehamster/tests/fixture/warnings.py
sqlalchemy_migrate_hotoffthehamster/versioning/__init__.py
sqlalchemy_migrate_hotoffthehamster/versioning/api.py
sqlalchemy_migrate_hotoffthehamster/versioning/cfgparse.py
sqlalchemy_migrate_hotoffthehamster/versioning/config.py
sqlalchemy_migrate_hotoffthehamster/versioning/genmodel.py
sqlalchemy_migrate_hotoffthehamster/versioning/migrate_repository.py
sqlalchemy_migrate_hotoffthehamster/versioning/pathed.py
sqlalchemy_migrate_hotoffthehamster/versioning/repository.py
sqlalchemy_migrate_hotoffthehamster/versioning/schema.py
sqlalchemy_migrate_hotoffthehamster/versioning/schemadiff.py
sqlalchemy_migrate_hotoffthehamster-0.14.3.dist-info/COPYING
sqlalchemy_migrate_hotoffthehamster-0.14.3.dist-info/METADATA
sqlalchemy_migrate_hotoffthehamster-0.14.3.dist-info/WHEEL
sqlalchemy_migrate_hotoffthehamster-0.14.3.dist-info/entry_points.txt
sqlalchemy_migrate_hotoffthehamster-0.14.3.dist-info/RECORD
