Metadata-Version: 2.1
Name: sqlalchemy-migrate-hotoffthehamster
Version: 0.14.3
Summary: Database schema migration for SQLAlchemy
License: MIT
Keywords: python,boilerplate,pyoilerplate,scaffolding,framework,CLI,TUI,skeleton,cookiecutter
Author: Landon Bouma
Author-email: doblabs@tallybark.com
Maintainer: Tally Bark LLC
Maintainer-email: doblabs@tallybark.com
Requires-Python: >=3.8.1,<4.0.0
Classifier: Development Status :: 5 - Production/Stable
Classifier: Intended Audience :: Developers
Classifier: License :: OSI Approved :: MIT License
Classifier: Natural Language :: English
Classifier: Operating System :: OS Independent
Classifier: Programming Language :: Python :: 3
Classifier: Programming Language :: Python :: 3.9
Classifier: Programming Language :: Python :: 3.10
Classifier: Programming Language :: Python :: 3.11
Classifier: Programming Language :: Python :: 3.12
Classifier: Topic :: Software Development :: Libraries :: Application Frameworks
Provides-Extra: readthedocs
Requires-Dist: decorator (>=5.1.1)
Requires-Dist: six (>=1.7.0)
Requires-Dist: sphinx (>=6.2.1,<7.0.0) ; (python_version >= "3.8" and python_version < "3.9") and (extra == "readthedocs")
Requires-Dist: sphinx (>=7.2.6,<8.0.0) ; (python_version >= "3.9" and python_version < "4.0") and (extra == "readthedocs")
Requires-Dist: sphinx-rtd-theme (>=2.0.0rc4,<3.0.0) ; extra == "readthedocs"
Requires-Dist: sqlalchemy (>=1.4.50,<1.5.0)
Requires-Dist: sqlparse (>=0.4.4,<0.5.0)
Requires-Dist: tempita-hotoffthehamster (>0)
Requires-Dist: tomli (>=2.0.1) ; extra == "readthedocs"
Project-URL: documentation, https://sqlalchemy-migrate-hotoffthehamster.readthedocs.io/en/latest
Project-URL: download, https://pypi.org/project/sqlalchemy-migrate-hotoffthehamster/#files
Project-URL: homepage, https://github.com/doblabs/sqlalchemy-migrate-hotoffthehamster
Project-URL: history, https://github.com/doblabs/sqlalchemy-migrate-hotoffthehamster/blob/release/HISTORY.rst
Project-URL: issues, https://github.com/doblabs/sqlalchemy-migrate-hotoffthehamster/issues
